[{"response": "[1,1,1,2,2,1,1,2,2,2,1,1,2,1,2,1,2,1,1,2,2,2,1,2,1,2,2,2,2,2,2,2,2,2,2,1,2,1,1,1,2,2,1,2,1,2,2,1,1,1,2,1,1,2,2,2,2,1,2,2,1,2,1,2,2,1,1,1,1,1,2,2,1,2,1,2,1,2,1,1,2,2,1,1,1,1,1,1,1,2,2,2,2,1,2,1,2,1,1,2]", "experiment": "Face", "feedback": "Certain combinations seemed a lot more likely", "time": 265.367999792099, "workerid": "A19IWME4DCIU1H", "stimuli": "[\"true-true-true\",\"true-true-true\",\"true-true-true\",\"true-false-false\",\"false-false-true\",\"true-true-true\",\"false-true-true\",\"true-true-false\",\"true-true-true\",\"true-true-false\",\"false-true-true\",\"false-true-true\",\"false-false-true\",\"false-true-true\",\"true-false-false\",\"false-true-true\",\"true-true-false\",\"true-true-true\",\"true-true-true\",\"false-false-true\",\"true-false-false\",\"true-false-false\",\"true-true-true\",\"true-false-false\",\"true-true-true\",\"true-false-false\",\"true-true-false\",\"true-true-false\",\"true-true-false\",\"true-false-false\",\"true-true-false\",\"true-false-true\",\"false-false-true\",\"true-false-false\",\"true-true-true\",\"true-true-true\",\"true-false-true\",\"false-true-true\",\"false-true-false\",\"false-true-false\",\"false-false-true\",\"false-false-true\",\"false-true-true\",\"false-false-true\",\"true-true-true\",\"false-false-true\",\"true-false-false\",\"false-true-false\",\"false-true-false\",\"false-true-false\",\"false-false-true\",\"true-true-true\",\"false-true-true\",\"false-false-true\",\"true-false-true\",\"false-false-true\",\"true-false-false\",\"false-true-false\",\"true-false-true\",\"true-false-true\",\"false-true-false\",\"false-false-true\",\"true-true-true\",\"true-false-false\",\"false-false-true\",\"true-true-true\",\"true-true-true\",\"false-true-false\",\"true-true-true\",\"false-true-false\",\"false-true-true\",\"true-false-true\",\"true-true-true\",\"true-false-true\",\"false-true-false\",\"false-false-true\",\"true-true-true\",\"true-false-true\",\"false-true-false\",\"true-true-true\",\"true-false-false\",\"false-false-true\",\"false-true-false\",\"false-true-false\",\"false-true-false\",\"true-true-true\",\"true-true-true\",\"true-true-true\",\"true-true-true\",\"true-false-false\",\"true-true-true\",\"true-false-false\",\"true-true-false\",\"true-true-true\",\"true-true-false\",\"false-true-false\",\"true-false-false\",\"true-true-true\",\"true-true-true\",\"true-false-true\"]", "sex": "Female", "age": "26", "truelabel": "[1,1,1,2,2,1,2,1,2,1,1,1,2,2,1,2,2,1,1,1,2,2,1,2,1,2,2,1,1,1,1,2,2,2,1,1,1,1,2,1,2,2,1,2,1,2,2,2,2,2,2,1,1,2,1,2,2,2,2,1,2,2,1,2,2,1,2,2,1,2,1,2,1,1,2,2,1,1,2,1,2,1,2,2,1,1,1,1,1,2,1,2,2,1,1,2,2,1,1,1]", "accuracy": 0.64000000000000001}, {"response": "[2,1,2,1,1,1,1,1,1,2,2,2,1,2,1,2,2,1,1,2,1,1,1,1,1,1,2,2,2,1,1,2,1,1,2,2,2,1,2,2,2,1,2,1,1,1,1,1,2,1,1,1,2,1,2,1,1,2,1,2,1,1,2,2,1,1,2,2,1,1,1,1,2,1,2,2,1,2,1,1,1,2,2,2,1,1,1,2,2,1,1,2,2,2,2,1,2,1,1,2]", "experiment": "Face", "feedback": "I tried to find things that were alike in certain families and group them together. I occasionally went against this because sometimes there were outliers. ", "time": 433.79499983787537, "workerid": "A1DS5O8MSI3ZH0", "stimuli": "[\"false-false-true\",\"true-true-false\",\"false-true-true\",\"true-false-false\",\"true-true-true\",\"true-true-true\",\"true-false-false\",\"true-true-true\",\"true-true-true\",\"false-true-false\",\"true-false-false\",\"false-false-true\",\"true-true-true\",\"false-true-true\",\"true-false-true\",\"true-true-true\",\"false-false-true\",\"true-false-false\",\"true-false-true\",\"false-false-true\",\"true-false-true\",\"true-true-true\",\"true-true-false\",\"true-true-true\",\"true-false-false\",\"true-true-true\",\"false-false-true\",\"false-false-true\",\"false-false-true\",\"true-true-false\",\"true-true-true\",\"false-true-false\",\"true-true-true\",\"true-true-true\",\"false-true-true\",\"true-false-false\",\"false-true-true\",\"true-false-false\",\"true-false-false\",\"true-false-false\",\"false-false-true\",\"true-true-true\",\"false-false-true\",\"true-true-true\",\"true-true-true\",\"true-false-true\",\"true-true-false\",\"false-true-false\",\"false-true-false\",\"true-true-true\",\"true-true-true\",\"true-true-false\",\"false-true-false\",\"true-false-false\",\"false-true-true\",\"true-true-true\",\"true-true-true\",\"false-false-true\",\"false-true-false\",\"true-true-false\",\"true-true-true\",\"true-false-true\",\"false-false-true\",\"false-true-true\",\"true-false-false\",\"true-true-true\",\"false-true-false\",\"true-false-false\",\"true-true-true\",\"true-false-false\",\"true-false-true\",\"false-false-true\",\"true-true-true\",\"true-true-false\",\"false-true-false\",\"false-true-false\",\"true-false-false\",\"false-false-true\",\"true-true-true\",\"true-false-true\",\"true-true-true\",\"false-true-false\",\"false-true-true\",\"false-false-true\",\"true-false-false\",\"true-true-true\",\"true-true-true\",\"false-true-true\",\"false-true-true\",\"true-false-true\",\"true-true-true\",\"false-true-false\",\"false-true-false\",\"false-false-true\",\"false-true-false\",\"true-false-true\",\"false-true-false\",\"true-true-false\",\"true-true-false\",\"false-true-false\"]", "sex": "Male", "age": "40", "truelabel": "[2,2,2,2,1,1,2,1,1,2,2,1,1,2,1,1,2,2,1,2,2,1,1,1,2,1,2,2,2,1,1,2,1,1,2,2,1,2,2,1,2,1,2,2,1,2,1,2,2,1,1,1,2,2,1,1,1,2,2,1,1,2,2,1,1,1,2,2,1,2,1,2,1,2,1,2,2,2,1,1,1,2,1,1,2,2,1,1,1,1,1,2,1,2,2,1,2,1,2,2]", "accuracy": 0.66000000000000003}, {"response": "[2,2,1,2,2,2,2,2,1,1,2,1,1,2,1,1,2,1,1,1,1,1,1,2,2,2,2,1,1,2,1,2,1,1,2,1,1,1,2,1,2,2,2,2,2,2,1,1,2,1,2,2,1,2,2,2,2,1,1,1,1,2,1,1,1,2,1,2,2,1,2,2,2,2,1,2,2,1,2,2,1,2,1,2,2,2,2,2,2,1,2,1,1,1,1,1,1,2,2,2]", "experiment": "Face", "feedback": "I just tried to keep track of how much certain combinations were appearing for each family.", "time": 344.26399993896484, "workerid": "A1FTGHYEU1T71Y", "stimuli": "[\"true-false-false\",\"false-true-false\",\"true-true-false\",\"false-true-false\",\"false-false-true\",\"false-true-false\",\"false-false-true\",\"false-false-true\",\"true-true-true\",\"false-true-true\",\"true-false-false\",\"true-true-true\",\"true-true-false\",\"true-false-false\",\"true-true-true\",\"true-true-true\",\"false-false-true\",\"true-true-true\",\"true-true-true\",\"true-true-false\",\"false-true-true\",\"true-true-false\",\"false-true-true\",\"false-false-true\",\"true-false-false\",\"true-false-false\",\"true-false-true\",\"true-true-false\",\"true-true-true\",\"false-true-false\",\"true-true-true\",\"false-false-true\",\"true-true-true\",\"false-true-true\",\"false-false-true\",\"true-true-true\",\"true-true-true\",\"true-true-true\",\"true-false-false\",\"false-true-false\",\"true-false-true\",\"false-true-false\",\"false-false-true\",\"true-false-true\",\"true-false-false\",\"true-false-false\",\"true-true-true\",\"true-true-true\",\"false-false-true\",\"true-true-true\",\"true-false-true\",\"false-true-false\",\"true-true-true\",\"false-true-false\",\"true-false-true\",\"true-false-true\",\"true-false-false\",\"true-true-true\",\"true-true-true\",\"false-true-true\",\"true-true-false\",\"true-false-true\",\"true-true-false\",\"true-true-true\",\"true-true-true\",\"true-false-true\",\"false-true-true\",\"false-true-false\",\"true-false-false\",\"true-true-true\",\"true-false-false\",\"true-false-true\",\"false-false-true\",\"false-false-true\",\"false-true-true\",\"true-true-true\",\"false-false-true\",\"true-true-true\",\"false-true-false\",\"false-false-true\",\"false-true-true\",\"false-true-false\",\"true-true-true\",\"true-false-false\",\"false-true-false\",\"false-true-false\",\"false-false-true\",\"false-true-false\",\"true-false-false\",\"true-true-false\",\"true-false-false\",\"true-true-false\",\"true-true-true\",\"false-true-true\",\"true-true-true\",\"true-true-true\",\"true-true-true\",\"true-false-false\",\"false-true-false\",\"false-false-true\"]", "sex": "Female", "age": "28", "truelabel": "[2,2,2,2,2,2,2,2,1,1,2,1,1,2,1,1,2,1,1,1,1,1,1,2,1,2,1,2,1,2,1,2,1,2,1,1,2,1,2,2,1,1,2,1,2,2,1,1,2,1,1,2,1,2,1,2,2,1,1,1,1,2,1,1,1,2,1,2,1,1,2,1,1,2,1,1,2,1,1,2,2,2,1,2,2,2,2,2,2,2,2,1,1,2,2,1,1,2,2,2]", "accuracy": 0.78000000000000003}, {"response": "[2,2,2,1,1,2,2,2,1,2,2,1,2,1,2,2,1,2,1,1,2,1,2,2,1,2,2,1,1,2,1,2,1,2,2,1,1,2,2,2,1,1,2,1,1,1,2,1,2,2,1,1,1,2,1,2,2,1,2,2,2,1,1,1,1,2,1,2,1,2,2,2,1,2,2,1,1,2,2,2,1,1,1,2,1,2,1,2,1,2,2,1,2,1,2,2,2,1,1,2]", "experiment": "Face", "feedback": "I first tried to find repeat patterns in the shapes that were being presented. I would make note of these and associate it with one number over then the other. I just tried to memorize the numbers and match with the shapes.", "time": 289.22100019454962, "workerid": "A3MHYBS6PHJ5QG", "stimuli": "[\"false-false-true\",\"false-true-true\",\"false-true-false\",\"true-true-true\",\"true-false-false\",\"false-true-false\",\"false-false-true\",\"true-false-false\",\"true-true-true\",\"true-true-true\",\"false-true-false\",\"false-true-true\",\"true-false-true\",\"true-true-true\",\"true-false-false\",\"true-true-false\",\"true-true-true\",\"true-false-false\",\"true-true-true\",\"true-false-true\",\"false-true-false\",\"true-true-true\",\"false-true-false\",\"false-true-false\",\"true-true-false\",\"false-true-true\",\"false-true-false\",\"true-false-true\",\"true-true-true\",\"false-false-true\",\"true-true-true\",\"false-false-true\",\"true-true-false\",\"false-true-false\",\"false-false-true\",\"false-true-true\",\"true-true-true\",\"false-false-true\",\"true-false-true\",\"true-false-true\",\"true-true-true\",\"true-true-false\",\"false-true-true\",\"true-true-true\",\"true-false-false\",\"true-true-true\",\"true-true-false\",\"true-true-true\",\"false-true-true\",\"false-true-true\",\"true-true-true\",\"true-true-true\",\"true-true-true\",\"true-false-false\",\"true-true-true\",\"false-false-true\",\"false-true-false\",\"true-false-false\",\"false-false-true\",\"false-true-false\",\"false-true-false\",\"true-true-true\",\"true-true-true\",\"true-true-true\",\"true-false-true\",\"false-true-false\",\"true-false-false\",\"true-false-true\",\"true-true-true\",\"true-false-true\",\"true-false-true\",\"false-false-true\",\"true-true-false\",\"false-true-true\",\"true-false-false\",\"true-true-true\",\"true-true-false\",\"false-true-true\",\"false-false-true\",\"false-true-false\",\"true-true-false\",\"true-true-true\",\"true-false-false\",\"true-false-false\",\"true-false-false\",\"false-false-true\",\"true-false-false\",\"false-false-true\",\"true-true-true\",\"false-false-true\",\"true-false-false\",\"true-true-true\",\"false-false-true\",\"true-true-true\",\"false-false-true\",\"false-true-false\",\"true-false-false\",\"true-true-true\",\"true-true-false\",\"false-true-false\"]", "sex": "Male", "age": "35", "truelabel": "[2,1,2,1,2,2,2,2,1,1,2,2,1,1,1,1,1,2,1,2,2,1,2,2,1,1,2,2,1,2,1,2,2,2,2,1,2,2,1,1,1,2,2,1,2,1,1,1,1,1,1,1,1,2,1,2,1,2,2,2,2,1,1,1,2,2,2,1,1,1,1,2,1,2,1,1,1,1,1,2,1,1,2,2,2,1,2,2,1,2,2,1,2,2,2,1,2,1,2,2]", "accuracy": 0.64000000000000001}, {"response": "[2,1,2,2,2,1,1,2,1,1,1,2,1,1,2,1,1,1,1,1,2,2,1,2,2,2,1,1,1,2,2,1,2,1,1,1,1,2,1,1,1,2,2,2,1,1,2,2,1,1,1,2,2,2,1,2,2,1,2,2,2,1,2,1,1,1,2,1,1,1,2,1,1,1,1,1,1,1,1,1,1,2,1,1,2,2,2,2,1,2,1,1,1,1,2,1,1,2,1,2]", "experiment": "Face", "feedback": "memorizing the patterns of 1 and 2s", "time": 321.33000016212463, "workerid": "A1ZKNQJO513B3W", "stimuli": "[\"false-false-true\",\"true-true-true\",\"true-false-false\",\"false-false-true\",\"true-false-false\",\"true-true-true\",\"false-true-true\",\"false-false-true\",\"false-true-true\",\"true-false-true\",\"true-true-true\",\"false-false-true\",\"true-true-true\",\"true-true-true\",\"false-true-false\",\"true-true-true\",\"true-false-false\",\"true-true-true\",\"true-true-true\",\"true-true-true\",\"false-false-true\",\"false-true-false\",\"true-true-false\",\"false-false-true\",\"true-false-false\",\"false-true-false\",\"true-false-false\",\"true-true-true\",\"true-true-true\",\"true-false-false\",\"false-true-false\",\"true-true-false\",\"true-false-false\",\"true-true-false\",\"true-true-true\",\"false-true-true\",\"true-false-true\",\"false-true-false\",\"true-false-true\",\"true-true-true\",\"true-true-false\",\"false-false-true\",\"false-false-true\",\"false-false-true\",\"true-true-false\",\"false-true-false\",\"true-false-false\",\"false-false-true\",\"true-true-true\",\"true-true-true\",\"true-false-true\",\"true-false-false\",\"false-false-true\",\"false-true-false\",\"true-true-false\",\"false-true-false\",\"true-true-true\",\"true-true-false\",\"false-true-false\",\"false-true-false\",\"false-false-true\",\"false-true-true\",\"false-true-false\",\"true-true-false\",\"false-true-true\",\"true-true-true\",\"true-false-false\",\"false-true-true\",\"false-false-true\",\"true-true-true\",\"true-false-false\",\"true-false-true\",\"true-false-true\",\"true-true-true\",\"true-true-true\",\"true-false-true\",\"true-true-true\",\"true-false-true\",\"true-true-true\",\"true-true-true\",\"false-true-true\",\"true-false-false\",\"false-true-true\",\"true-true-true\",\"false-true-false\",\"false-false-true\",\"false-true-false\",\"false-true-false\",\"true-true-true\",\"true-false-false\",\"false-true-true\",\"true-false-true\",\"true-true-true\",\"true-false-false\",\"false-false-true\",\"true-true-true\",\"true-true-true\",\"true-false-false\",\"true-true-false\",\"false-true-false\"]", "sex": "Male", "age": "31", "truelabel": "[2,1,1,2,2,1,1,2,2,1,1,2,1,1,2,1,2,1,1,1,2,2,1,2,2,1,2,2,1,2,2,2,2,1,1,1,1,2,2,1,1,1,2,2,2,2,2,2,1,1,2,2,2,2,1,2,1,1,2,2,2,1,2,1,1,1,2,2,2,1,2,1,1,1,1,1,1,2,2,1,1,2,1,1,2,1,2,2,1,2,2,1,1,2,2,1,1,1,2,1]", "accuracy": 0.77000000000000002}, {"response": "[2,1,1,1,2,1,1,2,1,2,2,1,1,2,2,1,1,1,2,2,1,2,2,1,2,1,2,2,2,1,1,1,2,2,2,1,2,2,2,2,2,1,2,2,1,1,2,2,1,1,1,1,2,1,2,2,2,2,2,2,2,2,2,1,1,1,1,1,1,1,2,2,2,2,2,2,1,1,1,2,1,2,1,2,2,2,2,2,2,1,2,1,1,2,1,2,2,2,2,2]", "experiment": "Face", "feedback": "Looked at the different features and what number had the most overall matches with it", "time": 382.90300011634827, "workerid": "A271BMHV42XZPU", "stimuli": "[\"true-false-false\",\"true-true-true\",\"true-true-true\",\"true-true-true\",\"false-true-false\",\"true-true-true\",\"true-true-false\",\"true-false-false\",\"true-true-true\",\"true-false-false\",\"true-false-false\",\"true-true-true\",\"true-true-true\",\"false-false-true\",\"false-false-true\",\"true-true-true\",\"true-true-true\",\"true-true-false\",\"false-false-true\",\"false-false-true\",\"true-true-false\",\"false-false-true\",\"false-true-false\",\"true-true-true\",\"false-false-true\",\"true-true-true\",\"false-false-true\",\"false-true-true\",\"false-false-true\",\"true-false-true\",\"true-true-true\",\"true-false-false\",\"false-false-true\",\"false-true-false\",\"true-false-false\",\"true-true-true\",\"false-false-true\",\"false-true-true\",\"true-false-false\",\"false-false-true\",\"false-true-false\",\"true-true-true\",\"false-true-false\",\"true-false-false\",\"true-true-true\",\"true-false-true\",\"false-true-true\",\"true-false-false\",\"true-true-true\",\"true-true-false\",\"true-true-false\",\"true-true-true\",\"false-false-true\",\"true-true-true\",\"false-true-false\",\"true-false-true\",\"false-true-false\",\"true-true-false\",\"true-false-true\",\"true-true-true\",\"false-true-false\",\"true-false-false\",\"true-false-false\",\"true-true-true\",\"true-true-true\",\"true-false-true\",\"true-true-true\",\"true-true-true\",\"true-true-true\",\"true-true-true\",\"false-true-false\",\"true-false-false\",\"false-true-false\",\"true-true-false\",\"true-false-true\",\"true-false-true\",\"false-true-true\",\"false-true-true\",\"true-false-true\",\"false-true-false\",\"true-true-true\",\"false-false-true\",\"true-true-true\",\"false-true-true\",\"false-false-true\",\"false-true-true\",\"false-true-false\",\"false-true-true\",\"false-true-true\",\"true-false-false\",\"true-false-false\",\"true-true-true\",\"true-false-true\",\"false-true-false\",\"true-true-false\",\"false-true-false\",\"false-true-false\",\"true-false-false\",\"true-true-false\",\"false-false-true\"]", "sex": "Male", "age": "26", "truelabel": "[2,1,1,1,2,1,1,2,1,2,2,1,1,2,2,1,1,2,2,2,2,2,2,1,2,1,2,2,2,1,1,2,2,1,2,1,2,2,2,1,2,1,2,2,1,1,1,2,2,1,1,1,2,1,2,2,2,1,2,1,2,2,1,1,1,1,1,1,1,2,2,2,2,1,1,1,1,1,2,2,1,2,1,1,2,1,2,2,1,1,2,1,1,2,2,2,1,2,1,1]", "accuracy": 0.78000000000000003}, {"response": "[1,1,1,2,2,1,1,2,2,2,1,1,2,1,2,1,2,1,1,2,2,2,1,2,1,2,2,2,2,2,2,2,2,2,2,1,2,1,1,1,2,2,1,2,1,2,2,1,1,1,2,1,1,2,2,2,2,1,2,2,1,2,1,2,2,1,1,1,1,1,2,2,1,2,1,2,1,2,1,1,2,2,1,1,1,1,1,1,1,2,2,2,2,1,2,1,2,1,1,2]", "experiment": "Face", "feedback": "Certain combinations seemed a lot more likely", "time": 265.367999792099, "workerid": "A19IWME4DCIU1H", "stimuli": "[\"true-true-true\",\"true-true-true\",\"true-true-true\",\"true-false-false\",\"false-false-true\",\"true-true-true\",\"false-true-true\",\"true-true-false\",\"true-true-true\",\"true-true-false\",\"false-true-true\",\"false-true-true\",\"false-false-true\",\"false-true-true\",\"true-false-false\",\"false-true-true\",\"true-true-false\",\"true-true-true\",\"true-true-true\",\"false-false-true\",\"true-false-false\",\"true-false-false\",\"true-true-true\",\"true-false-false\",\"true-true-true\",\"true-false-false\",\"true-true-false\",\"true-true-false\",\"true-true-false\",\"true-false-false\",\"true-true-false\",\"true-false-true\",\"false-false-true\",\"true-false-false\",\"true-true-true\",\"true-true-true\",\"true-false-true\",\"false-true-true\",\"false-true-false\",\"false-true-false\",\"false-false-true\",\"false-false-true\",\"false-true-true\",\"false-false-true\",\"true-true-true\",\"false-false-true\",\"true-false-false\",\"false-true-false\",\"false-true-false\",\"false-true-false\",\"false-false-true\",\"true-true-true\",\"false-true-true\",\"false-false-true\",\"true-false-true\",\"false-false-true\",\"true-false-false\",\"false-true-false\",\"true-false-true\",\"true-false-true\",\"false-true-false\",\"false-false-true\",\"true-true-true\",\"true-false-false\",\"false-false-true\",\"true-true-true\",\"true-true-true\",\"false-true-false\",\"true-true-true\",\"false-true-false\",\"false-true-true\",\"true-false-true\",\"true-true-true\",\"true-false-true\",\"false-true-false\",\"false-false-true\",\"true-true-true\",\"true-false-true\",\"false-true-false\",\"true-true-true\",\"true-false-false\",\"false-false-true\",\"false-true-false\",\"false-true-false\",\"false-true-false\",\"true-true-true\",\"true-true-true\",\"true-true-true\",\"true-true-true\",\"true-false-false\",\"true-true-true\",\"true-false-false\",\"true-true-false\",\"true-true-true\",\"true-true-false\",\"false-true-false\",\"true-false-false\",\"true-true-true\",\"true-true-true\",\"true-false-true\"]", "sex": "Female", "age": "26", "truelabel": "[1,1,1,2,2,1,2,1,2,1,1,1,2,2,1,2,2,1,1,1,2,2,1,2,1,2,2,1,1,1,1,2,2,2,1,1,1,1,2,1,2,2,1,2,1,2,2,2,2,2,2,1,1,2,1,2,2,2,2,1,2,2,1,2,2,1,2,2,1,2,1,2,1,1,2,2,1,1,2,1,2,1,2,2,1,1,1,1,1,2,1,2,2,1,1,2,2,1,1,1]", "accuracy": 0.64000000000000001}, {"response": "[1,2,1,1,2,2,2,2,2,2,1,1,2,1,1,2,2,2,1,1,1,1,1,2,1,1,2,2,1,2,1,2,1,1,1,1,1,2,2,1,2,2,2,2,2,2,2,2,2,2,2,1,2,1,1,1,1,1,1,2,2,2,1,2,1,1,2,1,2,1,1,1,1,1,2,2,1,2,2,1,1,1,2,2,1,1,2,2,2,1,2,2,1,2,1,1,1,1,2,2]", "experiment": "Face", "feedback": "Circle task - Family 2 seemed to have more where 2 and 3 features were visible and family 1 had more where just 1 feature was visible.\n\nFace task - Family 1 seemed to have more where just 1 feature was visible, while family 2 had more 2 and 3 feature images.", "time": 364.79999995231628, "workerid": "A2MCI9K0K5VX50", "stimuli": "[\"true-false-true\",\"false-true-false\",\"true-false-true\",\"true-true-true\",\"true-false-false\",\"true-false-false\",\"true-true-false\",\"false-true-false\",\"true-false-false\",\"false-true-false\",\"true-true-true\",\"true-true-true\",\"false-true-false\",\"true-true-true\",\"true-false-true\",\"false-false-true\",\"true-false-false\",\"true-true-true\",\"true-false-true\",\"true-false-true\",\"true-true-true\",\"true-true-true\",\"false-false-true\",\"false-true-false\",\"true-true-true\",\"true-false-true\",\"true-false-false\",\"true-true-false\",\"false-false-true\",\"false-false-true\",\"true-true-true\",\"false-false-true\",\"true-true-true\",\"true-true-true\",\"true-true-true\",\"true-false-true\",\"true-true-true\",\"false-false-true\",\"false-true-false\",\"true-true-true\",\"false-false-true\",\"false-false-true\",\"true-false-false\",\"false-true-false\",\"false-true-false\",\"false-true-false\",\"false-true-true\",\"false-false-true\",\"false-true-true\",\"true-true-true\",\"true-false-false\",\"true-false-true\",\"true-false-false\",\"true-true-false\",\"false-true-true\",\"true-true-false\",\"true-true-false\",\"true-false-false\",\"true-true-false\",\"false-false-true\",\"false-false-true\",\"true-false-false\",\"true-true-true\",\"false-true-true\",\"true-true-true\",\"true-true-true\",\"true-false-false\",\"true-true-true\",\"false-false-true\",\"false-true-true\",\"false-true-true\",\"true-true-true\",\"true-true-false\",\"false-true-true\",\"false-false-true\",\"true-false-false\",\"true-true-true\",\"false-true-false\",\"false-true-false\",\"true-true-true\",\"true-true-false\",\"true-true-false\",\"false-false-true\",\"true-false-false\",\"false-true-true\",\"true-true-true\",\"false-true-false\",\"true-false-false\",\"false-true-false\",\"true-true-true\",\"false-false-true\",\"false-true-true\",\"true-false-true\",\"false-true-false\",\"true-true-true\",\"true-true-true\",\"true-true-true\",\"true-true-true\",\"false-true-false\",\"true-false-false\"]", "sex": "Male", "age": "30", "truelabel": "[1,2,1,1,2,2,2,2,2,2,1,1,2,1,1,2,2,1,2,1,1,1,2,2,1,1,2,1,2,2,1,2,1,1,1,2,1,2,2,1,2,1,2,2,2,1,1,1,1,1,2,2,2,2,1,1,1,2,1,2,2,2,1,2,1,2,1,1,2,1,1,1,1,1,2,2,1,2,1,2,2,1,2,2,2,1,2,1,2,1,2,2,1,2,1,1,1,1,2,2]", "accuracy": 0.78000000000000003}, {"response": "[1,1,1,1,1,1,1,2,2,1,2,1,1,1,2,2,2,1,2,1,1,1,2,2,1,2,2,1,2,2,1,2,2,1,1,2,2,1,2,1,2,2,2,1,1,2,1,1,1,1,1,2,2,1,1,1,2,2,1,1,2,1,2,1,1,1,2,2,1,1,1,2,2,1,2,2,1,1,2,1,1,2,2,1,2,1,2,1,2,1,2,2,2,1,2,2,1,2,2,1]", "experiment": "Face", "feedback": "The relationships made no sense to me at all, genuinely.", "time": 241.73699998855591, "workerid": "A2SMZ45VAMIWW5", "stimuli": "[\"true-true-false\",\"false-false-true\",\"false-true-false\",\"true-true-true\",\"true-false-false\",\"false-false-true\",\"false-true-false\",\"true-false-false\",\"false-false-true\",\"true-false-false\",\"false-true-true\",\"true-false-false\",\"false-false-true\",\"false-false-true\",\"false-true-true\",\"true-true-true\",\"true-true-true\",\"false-true-false\",\"false-true-true\",\"true-true-true\",\"true-true-true\",\"true-true-false\",\"true-true-true\",\"true-false-false\",\"false-false-true\",\"true-true-true\",\"true-true-true\",\"false-false-true\",\"false-true-false\",\"true-true-true\",\"true-false-true\",\"false-true-false\",\"false-true-false\",\"true-true-false\",\"true-false-false\",\"true-true-true\",\"false-true-true\",\"true-true-false\",\"true-true-true\",\"true-false-true\",\"true-true-false\",\"true-true-true\",\"true-true-true\",\"false-true-true\",\"true-false-false\",\"true-true-true\",\"false-true-true\",\"true-true-false\",\"true-true-true\",\"false-true-false\",\"true-false-false\",\"true-true-true\",\"false-false-true\",\"true-true-true\",\"false-false-true\",\"false-false-true\",\"false-true-false\",\"true-true-true\",\"false-true-false\",\"true-false-false\",\"true-true-true\",\"false-true-false\",\"true-true-true\",\"false-false-true\",\"true-true-false\",\"false-true-false\",\"true-true-true\",\"false-true-true\",\"true-false-false\",\"true-true-true\",\"false-true-false\",\"true-true-true\",\"true-false-true\",\"true-false-false\",\"true-false-true\",\"false-false-true\",\"true-false-true\",\"false-true-false\",\"true-false-true\",\"true-false-false\",\"false-false-true\",\"true-true-true\",\"true-false-true\",\"false-true-false\",\"true-true-true\",\"true-false-false\",\"false-false-true\",\"false-true-false\",\"true-true-true\",\"true-false-false\",\"true-true-true\",\"false-true-true\",\"true-false-true\",\"true-true-false\",\"true-true-true\",\"false-false-true\",\"true-false-false\",\"true-false-true\",\"false-true-true\",\"true-true-false\"]", "sex": "Male", "age": "37", "truelabel": "[1,2,2,1,2,2,2,2,2,1,1,2,2,2,1,1,1,2,1,1,1,2,1,2,2,1,1,1,2,1,1,1,1,1,2,2,2,1,1,1,2,1,1,1,2,1,2,1,1,2,1,1,2,1,2,2,2,1,2,2,1,2,1,2,2,2,1,1,2,2,2,1,2,2,1,1,1,2,2,2,2,1,1,2,1,2,2,2,1,2,1,2,2,1,1,2,2,1,1,1]", "accuracy": 0.33000000000000002}, {"response": "[1,1,2,1,1,1,1,2,2,2,1,2,2,1,1,2,2,1,1,2,2,1,1,1,2,1,2,1,2,1,1,2,2,2,2,2,1,2,2,2,2,2,2,2,2,1,1,2,2,1,1,1,1,2,2,1,2,2,2,2,2,2,2,1,1,2,2,1,1,2,1,2,1,2,1,2,2,2,1,1,2,1,1,1,1,2,2,2,2,2,2,1,2,2,2,2,2,1,1,2]", "experiment": "Face", "feedback": "I tried to remember the ones that seemed mostly in one category or the other", "time": 291.52699995040894, "workerid": "A2W59CL4UQ3S4S", "stimuli": "[\"true-true-true\",\"true-true-true\",\"true-false-true\",\"true-true-false\",\"true-true-true\",\"true-true-false\",\"true-true-true\",\"true-false-false\",\"true-false-true\",\"true-false-true\",\"true-true-true\",\"false-false-true\",\"true-false-false\",\"true-false-true\",\"true-true-true\",\"true-true-false\",\"true-false-false\",\"true-true-false\",\"true-false-true\",\"true-false-true\",\"true-false-false\",\"true-true-true\",\"true-true-false\",\"true-true-true\",\"false-true-false\",\"true-true-false\",\"false-true-false\",\"true-true-true\",\"true-false-false\",\"true-true-true\",\"true-true-true\",\"false-false-true\",\"true-false-true\",\"false-true-true\",\"false-true-false\",\"false-true-false\",\"true-true-true\",\"false-true-true\",\"false-true-false\",\"false-true-false\",\"false-true-true\",\"false-true-true\",\"true-false-false\",\"false-true-true\",\"false-true-false\",\"true-false-true\",\"true-true-true\",\"false-false-true\",\"false-false-true\",\"true-true-true\",\"true-true-true\",\"true-true-true\",\"true-true-true\",\"false-false-true\",\"false-false-true\",\"true-true-true\",\"false-false-true\",\"false-true-false\",\"false-true-true\",\"false-true-false\",\"false-true-true\",\"false-false-true\",\"false-false-true\",\"true-true-false\",\"true-true-true\",\"true-false-false\",\"true-true-true\",\"true-true-true\",\"true-true-true\",\"true-false-false\",\"true-true-false\",\"false-true-false\",\"true-true-true\",\"true-false-false\",\"false-true-true\",\"false-true-false\",\"true-false-false\",\"true-true-true\",\"false-false-true\",\"true-false-true\",\"false-false-true\",\"true-true-true\",\"true-true-true\",\"true-true-true\",\"true-false-false\",\"true-false-false\",\"false-true-false\",\"false-true-false\",\"false-false-true\",\"false-false-true\",\"false-true-false\",\"true-false-false\",\"true-false-false\",\"false-false-true\",\"false-true-false\",\"true-false-false\",\"false-true-true\",\"true-true-false\",\"true-true-true\",\"false-false-true\"]", "sex": "Female", "age": "36", "truelabel": "[1,1,1,1,1,1,1,2,1,1,1,2,2,1,1,1,1,1,2,2,2,1,1,1,2,1,2,1,2,1,1,2,1,1,2,2,1,2,2,2,1,1,2,2,2,1,1,1,2,1,1,2,1,2,2,1,2,2,2,1,1,1,2,2,2,2,1,1,1,2,2,2,1,2,1,1,2,1,2,2,2,1,1,1,2,1,2,2,2,2,2,2,2,2,2,2,1,2,1,2]", "accuracy": 0.71999999999999997}, {"response": "[1,2,1,2,1,1,2,2,2,1,2,1,2,2,2,1,2,1,2,2,1,2,2,1,2,1,2,1,2,2,1,2,1,2,1,2,2,1,1,2,1,2,1,1,2,2,2,2,1,1,2,2,1,1,2,1,2,2,2,1,2,1,2,1,2,2,1,2,2,1,2,1,2,1,1,1,1,2,2,1,2,1,1,2,2,2,1,2,2,2,1,2,1,2,1,1,2,1,2,1]", "experiment": "Face", "feedback": "The first set of images I had noticed there were a couple certain patterns that were indicative of its belonging but on the second set I couldn't find any tell tale characteristics. ", "time": 294.69999980926519, "workerid": "A2YGAEODJ5SSF6", "stimuli": "[\"false-true-true\",\"true-false-false\",\"false-true-true\",\"true-true-true\",\"false-true-true\",\"true-true-true\",\"false-false-true\",\"false-false-true\",\"true-false-false\",\"true-true-true\",\"true-false-false\",\"true-true-true\",\"false-false-true\",\"true-true-true\",\"true-false-false\",\"true-true-false\",\"false-true-false\",\"false-false-true\",\"true-true-true\",\"false-true-false\",\"true-true-true\",\"true-true-true\",\"false-true-false\",\"false-true-false\",\"false-false-true\",\"true-false-true\",\"true-true-true\",\"true-true-true\",\"true-true-true\",\"true-true-true\",\"false-true-false\",\"true-true-true\",\"false-true-false\",\"false-true-true\",\"true-true-true\",\"false-true-false\",\"false-true-true\",\"false-true-false\",\"true-true-true\",\"true-false-false\",\"true-false-true\",\"true-true-false\",\"true-false-true\",\"true-true-true\",\"true-false-false\",\"true-false-false\",\"true-false-false\",\"false-false-true\",\"true-true-true\",\"true-true-true\",\"false-false-true\",\"true-true-false\",\"false-true-true\",\"true-true-false\",\"true-false-true\",\"true-true-false\",\"true-true-true\",\"false-false-true\",\"true-false-false\",\"true-true-true\",\"true-false-false\",\"true-true-true\",\"false-false-true\",\"true-true-true\",\"false-true-false\",\"true-false-false\",\"true-true-true\",\"false-true-false\",\"true-true-true\",\"false-false-true\",\"false-false-true\",\"true-false-true\",\"false-false-true\",\"true-true-false\",\"true-true-false\",\"true-true-false\",\"false-true-true\",\"false-false-true\",\"false-true-false\",\"false-true-false\",\"true-false-true\",\"true-false-true\",\"true-true-true\",\"false-false-true\",\"false-true-false\",\"false-true-false\",\"true-true-true\",\"true-true-true\",\"true-false-false\",\"true-false-false\",\"true-false-false\",\"true-true-false\",\"true-true-true\",\"false-true-false\",\"true-false-true\",\"false-true-true\",\"false-true-true\",\"true-false-false\",\"false-false-true\",\"true-false-true\"]", "sex": "Male", "age": "40", "truelabel": "[1,2,1,1,2,1,2,2,2,1,2,1,2,1,1,1,2,1,1,2,1,1,2,2,2,2,1,2,1,1,2,1,2,1,1,1,1,2,1,2,1,1,1,1,2,2,2,2,2,1,2,1,2,1,1,2,1,2,2,1,2,1,2,1,1,1,1,2,1,1,2,2,2,2,2,1,2,2,2,2,1,2,1,2,2,2,1,1,2,2,2,1,1,2,1,1,1,2,2,1]", "accuracy": 0.58999999999999997}, {"response": "[2,2,2,1,1,2,2,2,1,2,2,1,2,1,2,2,1,2,1,1,2,1,2,2,1,2,2,1,1,2,1,2,1,2,2,1,1,2,2,2,1,1,2,1,1,1,2,1,2,2,1,1,1,2,1,2,2,1,2,2,2,1,1,1,1,2,1,2,1,2,2,2,1,2,2,1,1,2,2,2,1,1,1,2,1,2,1,2,1,2,2,1,2,1,2,2,2,1,1,2]", "experiment": "Face", "feedback": "I first tried to find repeat patterns in the shapes that were being presented. I would make note of these and associate it with one number over then the other. I just tried to memorize the numbers and match with the shapes.", "time": 289.22100019454962, "workerid": "A3MHYBS6PHJ5QG", "stimuli": "[\"false-false-true\",\"false-true-true\",\"false-true-false\",\"true-true-true\",\"true-false-false\",\"false-true-false\",\"false-false-true\",\"true-false-false\",\"true-true-true\",\"true-true-true\",\"false-true-false\",\"false-true-true\",\"true-false-true\",\"true-true-true\",\"true-false-false\",\"true-true-false\",\"true-true-true\",\"true-false-false\",\"true-true-true\",\"true-false-true\",\"false-true-false\",\"true-true-true\",\"false-true-false\",\"false-true-false\",\"true-true-false\",\"false-true-true\",\"false-true-false\",\"true-false-true\",\"true-true-true\",\"false-false-true\",\"true-true-true\",\"false-false-true\",\"true-true-false\",\"false-true-false\",\"false-false-true\",\"false-true-true\",\"true-true-true\",\"false-false-true\",\"true-false-true\",\"true-false-true\",\"true-true-true\",\"true-true-false\",\"false-true-true\",\"true-true-true\",\"true-false-false\",\"true-true-true\",\"true-true-false\",\"true-true-true\",\"false-true-true\",\"false-true-true\",\"true-true-true\",\"true-true-true\",\"true-true-true\",\"true-false-false\",\"true-true-true\",\"false-false-true\",\"false-true-false\",\"true-false-false\",\"false-false-true\",\"false-true-false\",\"false-true-false\",\"true-true-true\",\"true-true-true\",\"true-true-true\",\"true-false-true\",\"false-true-false\",\"true-false-false\",\"true-false-true\",\"true-true-true\",\"true-false-true\",\"true-false-true\",\"false-false-true\",\"true-true-false\",\"false-true-true\",\"true-false-false\",\"true-true-true\",\"true-true-false\",\"false-true-true\",\"false-false-true\",\"false-true-false\",\"true-true-false\",\"true-true-true\",\"true-false-false\",\"true-false-false\",\"true-false-false\",\"false-false-true\",\"true-false-false\",\"false-false-true\",\"true-true-true\",\"false-false-true\",\"true-false-false\",\"true-true-true\",\"false-false-true\",\"true-true-true\",\"false-false-true\",\"false-true-false\",\"true-false-false\",\"true-true-true\",\"true-true-false\",\"false-true-false\"]", "sex": "Male", "age": "35", "truelabel": "[2,1,2,1,2,2,2,2,1,1,2,2,1,1,1,1,1,2,1,2,2,1,2,2,1,1,2,2,1,2,1,2,2,2,2,1,2,2,1,1,1,2,2,1,2,1,1,1,1,1,1,1,1,2,1,2,1,2,2,2,2,1,1,1,2,2,2,1,1,1,1,2,1,2,1,1,1,1,1,2,1,1,2,2,2,1,2,2,1,2,2,1,2,2,2,1,2,1,2,2]", "accuracy": 0.64000000000000001}, {"response": "[1,2,2,2,2,1,1,2,1,1,1,1,2,2,1,2,2,2,2,1,1,2,2,1,1,1,1,1,2,2,2,2,1,1,2,2,1,2,2,1,2,2,1,1,1,1,1,1,1,2,1,1,2,1,1,1,2,2,2,1,1,2,1,1,2,2,2,1,1,2,2,2,1,1,2,2,1,1,2,2,1,2,2,2,2,2,2,2,1,2,2,2,1,2,2,1,1,2,2,1]", "experiment": "Face", "feedback": "Of course, I used some cramming. I tried to memorize the shapes as much as possible.", "time": 326.36100006103521, "workerid": "ABC223", "stimuli": "[\"true-false-true\",\"false-false-true\",\"false-false-true\",\"false-false-true\",\"false-true-false\",\"true-true-true\",\"true-true-true\",\"false-true-false\",\"false-true-true\",\"true-true-true\",\"true-true-true\",\"true-true-false\",\"false-false-true\",\"true-false-true\",\"false-true-true\",\"true-false-true\",\"false-true-false\",\"true-false-false\",\"false-false-true\",\"true-true-true\",\"true-true-false\",\"false-true-false\",\"true-false-false\",\"true-true-true\",\"true-true-true\",\"false-true-true\",\"true-true-true\",\"false-true-true\",\"false-true-false\",\"false-true-false\",\"true-false-true\",\"false-false-true\",\"false-true-true\",\"true-true-true\",\"true-false-false\",\"false-true-false\",\"true-true-false\",\"true-false-false\",\"true-false-true\",\"true-true-true\",\"true-false-true\",\"false-false-true\",\"true-true-true\",\"true-true-false\",\"true-true-true\",\"true-true-true\",\"true-true-true\",\"true-true-true\",\"true-true-true\",\"true-false-true\",\"false-true-true\",\"true-true-true\",\"false-false-true\",\"true-true-false\",\"true-true-true\",\"true-true-false\",\"false-true-false\",\"false-false-true\",\"true-false-false\",\"true-true-true\",\"true-false-false\",\"true-false-true\",\"true-true-true\",\"true-true-true\",\"true-false-false\",\"false-true-false\",\"false-false-true\",\"true-true-false\",\"true-true-true\",\"true-false-false\",\"false-true-false\",\"false-false-true\",\"false-true-true\",\"true-true-true\",\"false-false-true\",\"false-true-false\",\"true-true-true\",\"true-true-true\",\"false-true-false\",\"false-false-true\",\"true-true-false\",\"false-false-true\",\"true-false-false\",\"true-false-false\",\"false-true-false\",\"true-false-false\",\"false-true-false\",\"false-true-true\",\"true-true-true\",\"false-true-false\",\"true-false-false\",\"true-false-false\",\"true-true-true\",\"true-false-false\",\"true-false-false\",\"true-true-false\",\"true-true-true\",\"true-false-true\",\"false-false-true\",\"false-true-true\"]", "sex": "Male", "age": "24", "truelabel": "[1,2,2,1,2,1,2,2,1,1,1,1,2,2,1,2,2,2,2,1,2,1,1,1,1,1,1,2,2,2,1,2,2,1,2,2,1,2,1,1,2,2,1,1,1,1,1,1,1,1,1,1,1,2,1,1,1,2,2,1,2,1,1,1,2,2,2,1,1,1,2,2,2,2,2,2,1,1,2,2,1,2,2,2,2,2,2,1,1,2,2,2,1,2,2,2,1,1,2,1]", "accuracy": 0.79000000000000004}, {"response": "[1,2,1,2,2,2,2,1,2,2,1,1,1,1,2,2,2,2,1,1,1,2,1,2,2,1,1,2,2,1,1,1,2,2,2,1,1,1,1,2,1,2,2,2,2,2,2,1,1,2,1,1,1,1,1,2,2,2,1,2,1,1,2,2,1,2,1,2,1,2,2,2,1,2,2,2,2,1,2,2,2,2,1,1,1,2,1,1,1,2,1,1,1,2,2,1,1,2,2,1]", "experiment": "Face", "feedback": "In experiment one Family 2 has more number of features then Family 1. Also the features lie mostly left in family 1 and vice versa on family 2. \nIn experiment two Family 1 has mostly complete face (more number of features) and family 2 has less. Family 2 has mostly eye and nose, though family one has eye and mouth and full face. ", "time": 396.81700015068049, "workerid": "ABC376", "stimuli": "[\"true-true-true\",\"true-true-false\",\"true-false-true\",\"false-true-false\",\"false-true-false\",\"false-true-true\",\"true-false-false\",\"true-true-true\",\"false-true-false\",\"false-false-true\",\"true-true-true\",\"true-true-true\",\"true-true-true\",\"false-false-true\",\"false-false-true\",\"true-false-false\",\"true-true-false\",\"false-false-true\",\"true-false-true\",\"true-true-true\",\"true-true-true\",\"true-false-false\",\"true-true-true\",\"false-true-false\",\"true-false-false\",\"true-true-true\",\"true-true-true\",\"false-true-false\",\"true-true-false\",\"true-true-true\",\"true-true-false\",\"true-true-true\",\"false-true-true\",\"false-true-false\",\"true-true-false\",\"true-true-false\",\"true-true-true\",\"false-true-true\",\"false-true-true\",\"false-true-true\",\"true-false-true\",\"true-false-false\",\"false-true-false\",\"true-false-false\",\"false-true-true\",\"false-true-true\",\"false-true-true\",\"true-true-true\",\"true-true-true\",\"false-false-true\",\"true-false-true\",\"true-true-true\",\"true-true-true\",\"false-false-true\",\"true-true-true\",\"true-false-true\",\"false-true-false\",\"false-true-false\",\"true-true-true\",\"false-false-true\",\"true-true-true\",\"true-true-false\",\"true-false-false\",\"true-true-false\",\"true-true-true\",\"true-false-false\",\"true-false-false\",\"false-false-true\",\"true-false-false\",\"false-true-false\",\"false-false-true\",\"false-true-false\",\"true-true-true\",\"false-true-false\",\"true-true-true\",\"true-false-false\",\"false-false-true\",\"true-true-true\",\"false-true-false\",\"true-false-false\",\"true-false-false\",\"true-false-false\",\"false-false-true\",\"true-false-true\",\"false-false-true\",\"false-true-false\",\"true-true-true\",\"true-false-true\",\"false-false-true\",\"false-true-false\",\"true-false-true\",\"false-false-true\",\"true-true-true\",\"true-true-true\",\"false-true-true\",\"true-false-true\",\"false-false-true\",\"true-false-false\",\"true-true-false\",\"true-true-true\"]", "sex": "Male", "age": "24", "truelabel": "[1,2,2,2,2,2,1,1,2,2,2,1,1,2,2,2,1,1,2,1,1,2,1,2,2,1,1,2,1,1,1,1,2,2,2,1,1,1,1,1,1,2,2,2,2,1,1,2,1,2,1,1,1,1,1,1,2,2,1,2,1,1,1,2,1,2,2,2,2,2,2,1,1,2,1,2,2,1,2,2,2,2,2,2,2,2,1,1,2,1,1,2,1,1,1,1,2,2,1,1]", "accuracy": 0.71999999999999997}, {"response": "[1,2,1,1,2,2,2,1,2,2,1,2,1,1,2,2,2,1,1,2,1,2,1,1,2,1,1,1,2,2,2,1,2,2,1,1,1,2,1,1,2,2,1,2,2,1,2,2,2,2,1,1,2,2,1,2,1,1,2,1,1,2,2,1,2,1,1,1,1,1,2,2,1,1,1,1,2,2,2,1,2,2,2,2,2,2,2,2,2,2,2,1,1,1,2,1,1,2,1,1]", "experiment": "Face", "feedback": "I tried to look for patterns of which family was likely to have one feature and which family was likely to have all three features", "time": 322.18099999427795, "workerid": "ABC544", "stimuli": "[\"false-true-true\",\"false-true-false\",\"true-true-true\",\"true-false-true\",\"false-false-true\",\"false-true-false\",\"true-false-false\",\"false-true-true\",\"false-false-true\",\"false-true-true\",\"true-false-true\",\"false-true-false\",\"true-true-true\",\"true-true-false\",\"false-true-false\",\"false-true-false\",\"false-true-true\",\"true-true-true\",\"false-false-true\",\"false-true-false\",\"true-true-true\",\"false-false-true\",\"true-true-true\",\"true-true-true\",\"true-false-false\",\"true-true-true\",\"true-true-true\",\"true-true-true\",\"true-false-false\",\"true-false-false\",\"false-true-true\",\"true-false-false\",\"false-false-true\",\"false-true-true\",\"true-true-false\",\"true-true-true\",\"true-true-true\",\"false-false-true\",\"true-true-true\",\"true-true-true\",\"true-false-false\",\"false-false-true\",\"true-true-true\",\"false-false-true\",\"true-false-false\",\"true-true-true\",\"false-true-false\",\"false-true-false\",\"false-false-true\",\"true-false-true\",\"true-true-false\",\"true-true-false\",\"false-true-false\",\"false-false-true\",\"true-true-false\",\"true-false-false\",\"true-true-true\",\"false-true-true\",\"false-true-false\",\"true-false-true\",\"true-true-true\",\"true-false-false\",\"true-true-false\",\"true-false-true\",\"false-false-true\",\"true-true-true\",\"true-true-true\",\"true-true-true\",\"true-true-true\",\"false-true-true\",\"false-false-true\",\"true-false-false\",\"true-true-true\",\"true-true-true\",\"true-false-true\",\"true-true-true\",\"false-true-false\",\"false-true-true\",\"false-true-false\",\"true-true-true\",\"true-false-false\",\"true-true-false\",\"false-true-false\",\"true-false-false\",\"false-true-false\",\"true-false-false\",\"true-false-true\",\"false-false-true\",\"true-false-false\",\"true-false-false\",\"true-true-false\",\"true-true-false\",\"true-true-true\",\"true-true-true\",\"false-false-true\",\"true-true-true\",\"false-false-true\",\"false-true-false\",\"true-false-true\",\"true-false-true\"]", "sex": "Female", "age": "27", "truelabel": "[1,1,1,2,1,1,1,1,2,2,1,2,1,2,2,2,2,1,2,2,1,2,1,1,2,1,1,1,2,2,1,2,2,1,2,1,2,2,1,1,2,1,1,2,2,1,2,2,2,1,1,1,2,2,1,2,1,1,2,2,1,1,1,1,2,1,1,1,1,1,2,2,1,2,2,1,2,2,2,1,2,2,2,2,2,2,1,2,2,2,1,1,1,1,2,1,2,2,1,1]", "accuracy": 0.78000000000000003}, {"response": "[2,2,1,2,2,1,1,2,2,2,2,1,1,2,2,1,1,1,1,1,1,2,2,1,2,2,2,2,1,1,1,1,2,1,1,1,2,1,2,2,2,2,1,1,1,1,2,1,1,2,2,1,2,2,1,2,1,2,1,2,2,2,1,2,1,1,1,2,1,2,2,1,2,1,2,1,1,2,1,1,2,1,1,1,2,2,2,1,1,1,2,1,1,1,1,2,1,2,1,2]", "experiment": "Face", "feedback": "i just tried to remember as i went through the sample. which family seemed to have more of the other. i think i maybe picked up on one pattern each family and then just picked that one.", "time": 323.57599997520452, "workerid": "ADIAEAPYRI8CK", "stimuli": "[\"false-true-false\",\"false-true-false\",\"true-true-false\",\"true-false-true\",\"true-false-false\",\"true-true-true\",\"true-true-true\",\"false-true-false\",\"false-false-true\",\"false-true-true\",\"false-false-true\",\"true-false-true\",\"true-false-false\",\"true-false-true\",\"false-true-true\",\"true-true-true\",\"true-true-true\",\"true-true-true\",\"false-true-false\",\"true-false-true\",\"true-true-true\",\"true-false-false\",\"false-true-true\",\"true-false-true\",\"true-true-false\",\"true-false-false\",\"false-true-true\",\"false-true-true\",\"true-true-true\",\"true-false-true\",\"true-true-true\",\"true-true-false\",\"false-false-true\",\"true-false-false\",\"true-false-false\",\"true-false-false\",\"false-false-true\",\"true-true-true\",\"false-true-false\",\"false-false-true\",\"false-true-true\",\"false-true-false\",\"true-true-true\",\"true-true-true\",\"true-true-true\",\"true-false-false\",\"false-true-false\",\"true-false-false\",\"true-true-true\",\"false-false-true\",\"false-false-true\",\"true-true-true\",\"false-false-true\",\"false-false-true\",\"true-true-false\",\"false-true-true\",\"true-false-false\",\"true-true-true\",\"true-true-true\",\"false-true-false\",\"false-true-false\",\"false-true-false\",\"true-true-true\",\"false-true-false\",\"true-true-true\",\"true-true-true\",\"true-true-true\",\"false-false-true\",\"true-false-false\",\"false-false-true\",\"false-false-true\",\"true-false-false\",\"false-true-false\",\"true-true-false\",\"false-true-false\",\"true-true-false\",\"true-true-true\",\"false-false-true\",\"true-true-true\",\"true-false-false\",\"true-true-true\",\"true-true-true\",\"true-true-true\",\"true-false-true\",\"false-true-true\",\"true-true-false\",\"true-true-false\",\"false-false-true\",\"true-false-true\",\"true-true-false\",\"false-true-false\",\"true-true-true\",\"true-true-true\",\"true-false-false\",\"true-false-false\",\"false-true-false\",\"true-false-true\",\"false-false-true\",\"true-true-true\",\"false-true-true\"]", "sex": "Female", "age": "45", "truelabel": "[2,1,1,2,2,1,1,1,2,2,1,2,2,2,1,1,1,1,2,1,1,2,2,1,2,2,2,1,1,1,1,1,2,1,2,1,2,1,2,2,1,2,1,1,1,2,2,2,1,2,2,2,2,2,1,1,2,1,1,2,2,2,1,2,1,1,2,1,2,2,2,2,2,1,2,2,1,2,1,2,1,1,1,1,1,1,1,2,1,2,2,1,1,2,2,2,1,2,1,1]", "accuracy": 0.68999999999999995}, {"response": "[1,1,2,1,2,1,2,1,1,1,2,1,2,2,2,2,1,2,1,2,2,2,2,1,2,1,1,1,1,2,1,2,2,2,1,1,2,1,1,2,2,1,2,2,2,2,2,2,2,1,2,1,2,1,1,2,2,2,2,1,2,2,1,2,1,1,2,2,2,2,1,1,1,1,2,2,1,1,2,1,2,1,1,1,2,1,2,1,1,2,2,2,2,2,1,1,1,1,2,1]", "experiment": "Face", "feedback": "I simply tried to figure repeating patterns", "time": 250.24000000953674, "workerid": "AEF74ZYJTTEIA", "stimuli": "[\"true-false-true\",\"true-false-true\",\"false-true-false\",\"true-true-true\",\"false-false-true\",\"true-true-true\",\"false-false-true\",\"true-true-true\",\"true-true-true\",\"true-true-false\",\"false-true-false\",\"true-true-true\",\"false-true-true\",\"false-true-true\",\"false-true-false\",\"false-true-false\",\"true-true-true\",\"true-false-false\",\"true-true-true\",\"false-false-true\",\"true-false-true\",\"false-true-false\",\"true-false-false\",\"true-true-false\",\"false-true-false\",\"true-true-true\",\"true-false-true\",\"true-true-true\",\"true-true-true\",\"false-true-false\",\"true-true-true\",\"true-false-false\",\"false-true-false\",\"false-true-false\",\"true-false-false\",\"true-true-false\",\"true-false-true\",\"true-true-false\",\"true-false-false\",\"false-true-false\",\"false-false-true\",\"true-true-true\",\"false-false-true\",\"false-false-true\",\"true-false-true\",\"false-true-false\",\"true-false-false\",\"false-false-true\",\"false-false-true\",\"true-true-true\",\"false-true-true\",\"true-true-true\",\"false-true-false\",\"false-true-true\",\"false-true-true\",\"true-false-true\",\"false-false-true\",\"false-true-false\",\"false-false-true\",\"true-false-false\",\"true-false-false\",\"true-false-false\",\"true-true-true\",\"true-false-false\",\"true-true-false\",\"true-true-true\",\"false-false-true\",\"false-false-true\",\"true-false-false\",\"false-false-true\",\"true-true-false\",\"true-true-false\",\"false-true-true\",\"true-true-false\",\"true-false-false\",\"false-true-true\",\"true-true-true\",\"true-true-true\",\"false-true-true\",\"true-true-true\",\"false-true-false\",\"true-true-true\",\"true-true-true\",\"true-true-true\",\"false-true-false\",\"true-false-false\",\"true-true-false\",\"true-false-true\",\"true-true-true\",\"true-false-false\",\"true-false-true\",\"false-true-true\",\"false-false-true\",\"false-false-true\",\"true-true-true\",\"true-true-true\",\"true-true-true\",\"true-true-true\",\"true-false-false\",\"true-true-true\"]", "sex": "Male", "age": "39", "truelabel": "[1,1,2,2,2,1,2,1,1,1,1,1,1,1,2,2,1,2,1,1,2,1,1,2,2,1,2,1,1,2,1,1,2,2,2,1,1,2,2,2,2,1,2,2,2,2,2,2,2,1,1,1,2,1,2,1,2,2,2,2,2,2,1,2,2,1,1,2,2,2,1,1,1,1,2,1,1,1,2,1,2,1,1,1,2,2,1,1,1,2,1,2,2,2,2,1,1,1,2,1]", "accuracy": 0.75}, {"response": "[1,2,1,1,2,2,1,2,2,1,1,1,1,1,1,1,2,2,2,2,2,1,2,2,2,2,2,1,2,2,2,2,2,1,2,1,2,2,1,1,1,2,2,2,2,2,2,2,1,1,1,2,2,1,1,2,1,1,2,1,2,1,2,1,2,1,2,1,1,1,1,2,1,2,2,1,2,1,1,2,1,2,2,2,1,2,2,2,1,1,2,1,1,1,2,1,1,2,2,2]", "experiment": "Face", "feedback": "tried to memorize what was more frequent for the family and stick with that for the most part", "time": 367.25499987602234, "workerid": "AIJUY02ENAH9U", "stimuli": "[\"true-true-true\",\"false-true-false\",\"true-true-false\",\"false-true-true\",\"false-false-true\",\"false-true-false\",\"true-true-true\",\"true-false-false\",\"true-false-true\",\"true-true-true\",\"true-true-true\",\"true-true-true\",\"true-true-true\",\"true-true-true\",\"true-true-true\",\"true-true-true\",\"true-false-false\",\"false-false-true\",\"false-true-false\",\"false-false-true\",\"true-true-true\",\"true-true-true\",\"false-false-true\",\"false-false-true\",\"false-true-false\",\"true-false-false\",\"true-false-false\",\"true-false-true\",\"true-false-false\",\"false-true-false\",\"true-true-false\",\"false-false-true\",\"true-false-false\",\"true-false-true\",\"true-true-true\",\"true-true-true\",\"false-true-false\",\"false-true-false\",\"true-true-true\",\"true-true-false\",\"true-false-true\",\"true-false-false\",\"true-true-false\",\"true-false-false\",\"true-true-false\",\"false-true-false\",\"true-false-false\",\"true-false-true\",\"true-true-true\",\"true-true-true\",\"false-true-true\",\"false-true-false\",\"false-true-false\",\"true-true-true\",\"false-false-true\",\"false-true-false\",\"true-true-true\",\"false-false-true\",\"true-false-true\",\"false-true-true\",\"false-true-false\",\"false-true-true\",\"true-false-false\",\"false-true-true\",\"true-false-false\",\"true-true-true\",\"true-false-false\",\"true-true-true\",\"false-true-true\",\"true-true-true\",\"true-true-true\",\"false-true-false\",\"true-true-true\",\"false-false-true\",\"true-true-false\",\"true-false-true\",\"true-true-false\",\"true-true-true\",\"true-true-true\",\"true-false-true\",\"false-false-true\",\"false-true-false\",\"false-false-true\",\"false-false-true\",\"true-true-true\",\"true-false-false\",\"true-false-false\",\"false-true-false\",\"true-true-true\",\"false-true-true\",\"false-false-true\",\"true-true-false\",\"true-true-true\",\"true-true-false\",\"false-false-true\",\"false-false-true\",\"true-false-true\",\"true-false-false\",\"false-true-true\",\"false-true-true\"]", "sex": "Female", "age": "33", "truelabel": "[1,2,2,2,2,2,1,2,1,1,1,2,2,1,1,1,2,2,1,2,1,1,1,2,2,2,2,1,2,2,2,2,2,2,1,1,2,2,1,1,1,2,2,2,1,2,2,1,1,1,1,2,2,1,2,2,1,2,1,1,1,2,2,2,1,1,1,1,1,1,1,2,1,2,1,2,1,1,1,1,2,2,2,2,1,2,2,2,1,1,2,1,1,1,2,1,2,2,1,1]", "accuracy": 0.71999999999999997}, {"response": "[1,1,2,2,1,2,1,1,2,1,1,2,1,1,2,2,1,1,1,1,2,2,2,1,2,2,1,2,1,2,2,2,1,2,1,2,1,1,1,2,1,1,2,2,1,1,2,1,2,1,2,1,2,1,1,1,2,1,2,2,2,1,2,2,1,2,1,2,2,2,2,1,1,1,2,2,1,2,1,2,2,1,1,1,1,2,1,2,2,1,2,1,1,2,1,2,1,2,1,2]", "experiment": "Face", "feedback": "I tried to count the number of times I saw certain features, but it's hard to keep track of mentally. No doubt some of my answers cross such as family 1 a few times, then I say family 2 a few times. Honestly, that was my only strategy.", "time": 362.41100001335138, "workerid": "AIZTLQM7HHQN6", "stimuli": "[\"true-true-true\",\"true-true-true\",\"false-true-false\",\"false-false-true\",\"true-true-true\",\"true-false-true\",\"true-true-true\",\"true-true-true\",\"false-true-true\",\"true-true-true\",\"true-true-false\",\"true-true-false\",\"true-true-true\",\"true-true-true\",\"true-false-true\",\"false-false-true\",\"true-false-false\",\"true-true-false\",\"true-true-true\",\"true-true-true\",\"true-false-false\",\"true-false-false\",\"true-false-true\",\"false-true-false\",\"true-false-false\",\"false-true-false\",\"false-false-true\",\"true-false-true\",\"true-true-true\",\"true-false-false\",\"true-true-true\",\"true-true-true\",\"false-true-false\",\"false-false-true\",\"true-false-false\",\"true-true-false\",\"false-true-false\",\"false-false-true\",\"false-true-true\",\"false-false-true\",\"true-true-true\",\"true-true-true\",\"false-false-true\",\"true-false-true\",\"true-true-false\",\"false-true-false\",\"false-true-true\",\"true-false-true\",\"false-true-true\",\"false-true-false\",\"true-true-true\",\"true-true-false\",\"true-false-false\",\"false-false-true\",\"true-true-false\",\"false-true-true\",\"false-true-false\",\"true-true-true\",\"false-false-true\",\"false-false-true\",\"true-true-false\",\"true-true-true\",\"false-true-false\",\"false-false-true\",\"true-false-false\",\"false-true-false\",\"true-false-false\",\"false-true-true\",\"true-false-false\",\"false-true-false\",\"false-false-true\",\"true-true-true\",\"true-true-true\",\"true-true-true\",\"false-true-true\",\"true-false-false\",\"false-true-true\",\"false-false-true\",\"true-true-true\",\"false-true-false\",\"false-false-true\",\"false-false-true\",\"false-true-false\",\"true-false-true\",\"true-true-true\",\"true-false-false\",\"false-true-true\",\"false-true-false\",\"true-true-true\",\"true-false-true\",\"true-false-false\",\"true-false-true\",\"true-true-false\",\"true-true-true\",\"true-true-true\",\"true-false-false\",\"true-true-true\",\"false-true-false\",\"true-true-true\",\"true-false-false\"]", "sex": "Male", "age": "26", "truelabel": "[1,1,2,2,1,2,1,1,2,1,2,1,1,1,1,2,2,2,1,1,2,2,2,2,2,1,2,1,1,2,2,1,2,2,2,1,2,2,1,2,1,1,1,1,1,2,2,2,1,2,1,1,2,2,2,1,2,1,2,2,1,1,2,2,1,1,2,2,2,2,1,1,1,1,1,2,1,2,1,2,2,2,2,1,1,1,1,2,1,1,2,1,1,2,1,2,1,2,1,2]", "accuracy": 0.67000000000000004}, {"response": "[2,2,1,2,2,1,1,1,1,1,1,2,2,1,2,1,2,1,1,2,2,1,1,2,1,1,2,1,1,2,2,1,1,1,1,1,1,2,1,2,2,1,2,2,1,1,2,1,2,1,2,2,1,1,2,1,1,2,1,1,2,1,1,2,2,1,2,1,1,2,1,1,1,1,2,1,1,2,1,2,1,1,1,2,1,2,1,2,2,2,2,2,1,2,1,2,2,2,1,2]", "experiment": "Face", "feedback": "I tried to memorized the practice patterns ", "time": 299.16599988937384, "workerid": "AN22ISWT92XQ8", "stimuli": "[\"true-false-false\",\"true-true-false\",\"true-true-true\",\"true-false-false\",\"true-false-false\",\"false-true-false\",\"true-true-true\",\"true-true-true\",\"false-true-false\",\"false-false-true\",\"true-false-true\",\"false-false-true\",\"false-true-false\",\"true-true-true\",\"false-true-false\",\"true-true-true\",\"true-false-false\",\"true-true-true\",\"true-true-true\",\"false-false-true\",\"false-true-false\",\"true-true-true\",\"false-true-true\",\"false-true-false\",\"false-true-false\",\"false-false-true\",\"true-true-false\",\"true-true-true\",\"true-true-true\",\"false-false-true\",\"false-false-true\",\"true-true-true\",\"true-true-false\",\"true-true-true\",\"true-false-true\",\"true-true-false\",\"true-false-true\",\"false-false-true\",\"true-true-true\",\"true-false-true\",\"false-false-true\",\"true-false-true\",\"true-false-false\",\"true-true-false\",\"false-true-false\",\"true-true-true\",\"false-true-false\",\"false-false-true\",\"true-true-true\",\"true-true-true\",\"false-true-true\",\"true-false-false\",\"false-false-true\",\"false-true-true\",\"false-true-false\",\"true-false-true\",\"true-true-true\",\"true-true-true\",\"true-true-true\",\"false-true-false\",\"true-false-true\",\"false-true-true\",\"true-true-true\",\"false-false-true\",\"false-true-false\",\"true-true-true\",\"true-false-false\",\"true-true-true\",\"true-true-true\",\"true-false-true\",\"true-true-true\",\"true-true-false\",\"true-false-false\",\"false-true-true\",\"true-true-true\",\"true-false-true\",\"true-false-false\",\"false-false-true\",\"true-false-false\",\"false-true-false\",\"false-true-true\",\"false-true-false\",\"false-false-true\",\"true-true-false\",\"false-true-true\",\"true-false-false\",\"false-true-true\",\"true-false-false\",\"true-false-false\",\"true-true-false\",\"true-false-false\",\"true-true-false\",\"true-true-true\",\"true-true-true\",\"true-true-true\",\"false-false-true\",\"false-true-false\",\"false-true-true\",\"true-false-false\",\"false-false-true\"]", "sex": "Male", "age": "25", "truelabel": "[1,1,1,2,2,2,1,2,2,2,2,1,2,1,2,1,2,1,1,2,2,1,1,1,2,2,1,1,1,2,2,1,1,1,1,1,1,2,1,1,2,1,2,2,2,1,2,2,1,2,1,2,2,1,2,2,1,1,1,2,1,1,1,2,1,1,2,1,1,2,1,1,2,1,1,1,1,2,2,2,2,2,1,2,1,2,2,2,2,1,2,2,1,1,1,2,2,2,2,2]", "accuracy": 0.67000000000000004}]